que_sdk/__init__.py
que_sdk/_internal/__init__.py
que_sdk/_internal/auth.py
que_sdk/_internal/base.py
que_sdk/client.py
que_sdk/clients.py
que_sdk/py.typed.py
que_sdk/schemas.py
que_sdk/types.py
que_sdk-0.2.9.dist-info/LICENSE
que_sdk-0.2.9.dist-info/METADATA
que_sdk-0.2.9.dist-info/WHEEL
que_sdk-0.2.9.dist-info/RECORD
