Metadata-Version: 2.1
Name: que_sdk
Version: 0.2.9
Summary: 
License: MIT
Author: DavidRomanovizc
Requires-Python: >=3.11,<4.0
Classifier: License :: OSI Approved :: MIT License
Classifier: Programming Language :: Python :: 3
Classifier: Programming Language :: Python :: 3.11
Classifier: Programming Language :: Python :: 3.12
Requires-Dist: backoff (>=2.2.1,<3.0.0)
Requires-Dist: httpx (>=0.27.0,<0.28.0)
